Metadata-Version: 2.1
Name: python-app
Version: 0.1
Summary: air connection app
Home-page: http://gitlab-1914910442.us-west-2.elb.amazonaws.com/vverkholyak/python_app
Author: vverholyak
License: UNKNOWN
Platform: UNKNOWN
Classifier: Programming Language :: Python :: 3
Classifier: Operating System :: OS Independent
Requires-Python: >=3.6
